{
  "factions": [
    {
      "name": "Naval Forces",
      "tags": [
        "[KNF]",
        "IKN-",
        "KDS-",
        "Serpent-"
      ],
      "alwaysDisplay": true
    },
    {
      "name": "Blood Dragons",
      "tags": [
        "BD|",
        "n~}",
        "KA|"
      ],
      "alwaysDisplay": false
    },
    {
      "name": "State Police",
      "tags": [
        "[KSP]",
        "(KSP)"
      ],
      "alwaysDisplay": false
    },
    {
      "name": "Golden Chrysanthemums",
      "tags": [
        "GC|"
      ],
      "alwaysDisplay": false
    },
    {
      "name": "Kishiro",
      "tags": [
        "Kishiro|"
      ],
      "alwaysDisplay": false
    },
    {
      "name": "Samura",
      "tags": [
        "Samura|-",
        "TsuSec|"
      ],
      "alwaysDisplay": false
    },
    {
      "name": "Hogosha",
      "tags": [
        "[HA]"
      ],
      "alwaysDisplay": false
    },
    {
      "name": "Hanta Iseijin 113th",
      "tags": [
        "|Aoi"
      ],
      "alwaysDisplay": false
    },
    {
      "name": "Corsairs",
      "tags": [
        "C::",
        "[TBH]",
        "CNS-"
      ],
      "alwaysDisplay": false
    },
    {
      "name": "Defilers",
      "tags": [
        "Defiler."
      ],
      "alwaysDisplay": false
    },
    {
      "name": "Lane Hackers",
      "tags": [
        "LH~"
      ],
      "alwaysDisplay": false
    },
    {
      "name": "Casa Loyola",
      "tags": [
        "Loyola"
      ],
      "alwaysDisplay": false
    },
    {
      "name": "Outcasts",
      "tags": [
        "(C~",
        "MNS-"
      ],
      "alwaysDisplay": false
    },
    {
      "name": "Mercenaries",
      "tags": [
        "Forlorn|-"
      ],
      "alwaysDisplay": false
    },
    {
      "name": "Rheinland Forces",
      "tags": [
        "[RM]",
        "BDM|",
        "RNC-"
      ],
      "alwaysDisplay": false
    }
  ],
  "regions": [
    {
      "name": "Kusari",
      "systems": [
        "Nagano",
        "Chugoku",
        "Tohoku",
        "Rishiri",
        "Tottori",
        "Hokkaido",
        "Hiroshima",
        "New Tokyo",
        "Honshu",
        "Kyushu",
        "Shikoku"
      ],
      "alwaysDisplay": true,
      "showPlayers": false
    },
    {
      "name": "Liberty border",
      "systems": [
        "Kepler",
        "Galileo"
      ],
      "alwaysDisplay": false,
      "showPlayers": false
    },
    {
      "name": "Taus",
      "systems": [
        "Tau-29",
        "Tau-37",
        "Tau-23",
        "Tau-44"
      ],
      "alwaysDisplay": false,
      "showPlayers": false
    },
    {
      "name": "Sigmas",
      "systems": [
        "Sigma-19",
        "Sigma-13",
        "Sigma-21",
        "Sigma-17",
        "Okinawa"
      ],
      "alwaysDisplay": false,
      "showPlayers": false
    },
    {
      "name": "Unknown space",
      "systems": [
        "Uncharted Kusari"
      ],
      "alwaysDisplay": false,
      "showPlayers": false
    }
  ],
  "guildSettings": {
    "messagesImage": "https://i.imgur.com/V16L8i9.jpg",
    "messagesFooterName": "Kusari Kaigun",
    "scanMainRegionName": "House Kusari",
    "acknowledged": "Ryoukai!",
    "mainChannelName": "bots",
    "adminChannelName": "admiralty",
    "emergencyChannelName": "emergency",
    "activityNoticeMinPlayers": 3,
    "activityNoticeMessages": [
      "omae wa mou shindeiru",
      "Weebs detected",
      "Kill all the animu",
      "There is some activity in Kusari!",
      "Bakas spotted"
    ],
    "commandsPrefix": "!"
  }
}